pyhaven/__init__.py
pyhaven/__main__.py
pyhaven/expADB/__init__.py
pyhaven/expAI/__init__.py
pyhaven/expAlgorithm/__init__.py
pyhaven/expAutomation/__init__.py
pyhaven/expDatetime/__init__.py
pyhaven/expGraph/__init__.py
pyhaven/expMC/__init__.py
pyhaven/expMath/__init__.py
pyhaven/expPackage/__init__.py
pyhaven/expString/__init__.py
pyhaven/expString/expString.py
pyhaven/expString/test_text2pinyin.py
pyhaven/expTools/__init__.py
pyhaven/expTools/__init__bak.py
pyhaven/expWebcrawler/__init__.py
pyhaven-0.0.4.dist-info/METADATA
pyhaven-0.0.4.dist-info/WHEEL
pyhaven-0.0.4.dist-info/top_level.txt
pyhaven-0.0.4.dist-info/RECORD
