Metadata-Version: 2.1
Name: pyhaven
Version: 0.0.4
Summary: This is the package used to explore Python.
Home-page: 
Author: mingwei
Author-email: mingwe.me@qq.com
Keywords: explore,python,development
Classifier: Development Status :: 3 - Alpha
Classifier: Intended Audience :: Developers
Classifier: Topic :: Software Development :: Build Tools
Classifier: License :: OSI Approved :: MIT License
Classifier: Programming Language :: Python :: 3
Classifier: Programming Language :: Python :: 3.7
Classifier: Programming Language :: Python :: 3.8
Classifier: Programming Language :: Python :: 3.9
Classifier: Programming Language :: Python :: 3.10
Classifier: Programming Language :: Python :: 3 :: Only
Requires-Python: >=3.12, <4
Requires-Dist: pyperclip
Requires-Dist: requests
Requires-Dist: pyautogui
Requires-Dist: bs4
Requires-Dist: pyttsx3
Requires-Dist: pypinyin
